wordmesh/__init__.py
wordmesh/force_directed_model.py
wordmesh/static_wordmesh.py
wordmesh/stopwords.txt
wordmesh/text_processing.py
wordmesh/utils.py
wordmesh-0.1.0b2.dist-info/METADATA
wordmesh-0.1.0b2.dist-info/RECORD
wordmesh-0.1.0b2.dist-info/WHEEL
wordmesh-0.1.0b2.dist-info/top_level.txt
