Metadata-Version: 2.1
Name: wordmesh
Version: 0.1.0b2
Summary: A wordcloud generator which allows for meaningful word clustering
Home-page: https://github.com/mukund109/word-mesh
Author: Mukund Chaudhry
Author-email: mukund.chaudhry@gmail.com
License: MIT
Platform: UNKNOWN
Requires-Python: >=3
Requires-Dist: textacy (>=0.6.1)
Requires-Dist: plotly (>=2.0.11)
Requires-Dist: numpy (>=1.12.0)
Requires-Dist: colorlover (==0.2.1)
Requires-Dist: pandas (>=0.19.2)
Requires-Dist: scipy (>=0.18.1)
Requires-Dist: scikit-learn
